deviceid/__init__.py
deviceid/_store.py
deviceid/deviceid.py
py_deviceid-0.1.0.dist-info/LICENSE.txt
py_deviceid-0.1.0.dist-info/METADATA
py_deviceid-0.1.0.dist-info/WHEEL
py_deviceid-0.1.0.dist-info/top_level.txt
py_deviceid-0.1.0.dist-info/RECORD
