Metadata-Version: 2.1
Name: py-deviceid
Version: 0.1.0
Summary: A simple library to get or create a unique device id for a device in Python.
Author-email: Microsoft Corporation <vstelinstr@microsoft.com>
License: py-deviceid
Project-URL: Repository, https://github.com/microsoft/py-deviceid
Classifier: Development Status :: 3 - Alpha
Classifier: Programming Language :: Python :: 3 :: Only
Classifier: Programming Language :: Python :: 3
Classifier: Programming Language :: Python :: 3.8
Classifier: Programming Language :: Python :: 3.9
Classifier: Programming Language :: Python :: 3.10
Classifier: Programming Language :: Python :: 3.11
Classifier: Programming Language :: Python :: 3.12
Classifier: License :: OSI Approved :: MIT License
Requires-Python: >=3.8
License-File: LICENSE.txt
